nonebot_plugin_ability-0.1.0.dist-info/METADATA
nonebot_plugin_ability-0.1.0.dist-info/WHEEL
nonebot_plugin_ability/__init__.py
nonebot_plugin_ability/message.py
nonebot_plugin_ability/requests/__init__.py
nonebot_plugin_ability/requests/fake_user_agent.json
nonebot_plugin_ability/requests/utils.py
nonebot_plugin_ability/text.py
nonebot_plugin_ability/utils.py
nonebot_plugin_ability-0.1.0.dist-info/RECORD
