Metadata-Version: 2.1
Name: nonebot-plugin-ability
Version: 0.1.0
Summary: NoneBot 外置电池
Author-Email: Komorebi <mute231010@gmail.com>
License: MIT
Requires-Python: >=3.10
Requires-Dist: httpx>=0.25.0
Requires-Dist: nonebot2[fastapi]>=2.1.0
Requires-Dist: nonebot-plugin-alconna>=0.25.1
Requires-Dist: ujson>=5.8.0
